{"metadata": {"dbt_schema_version": "https://schemas.getdbt.com/dbt/run-results/v4.json", "dbt_version": "1.0.8", "generated_at": "2022-07-29T11:25:39.438567Z", "invocation_id": "c87396a1-3193-4bd6-9fc6-4a447c319699", "env": {}}, "results": [{"status": "success", "timing": [{"name": "compile", "started_at": "2022-07-29T11:22:59.995744Z", "completed_at": "2022-07-29T11:25:35.215767Z"}, {"name": "execute", "started_at": "2022-07-29T11:25:35.216242Z", "completed_at": "2022-07-29T11:25:39.349206Z"}], "thread_id": "Thread-1", "execution_time": 159.43983387947083, "adapter_response": {"_message": "SUCCESS 1", "code": "SUCCESS", "rows_affected": 1}, "message": "SUCCESS 1", "failures": null, "unique_id": "model.OI_Foundation._foundation_load_config"}], "elapsed_time": 160.94041323661804, "args": {"write_json": true, "use_colors": true, "printer_width": 80, "version_check": true, "partial_parse": true, "static_parser": true, "profiles_dir": "/usr/src/develop/.dbt", "send_anonymous_usage_stats": true, "event_buffer_size": 100000, "vars": "{}\n", "select": ["models/support_tables"], "which": "run", "rpc_method": "run", "indirect_selection": "eager"}}